{
    "/js/teams/single.js": "/js/teams/single.js?id=28ec2c47e2bc54150972",
    "/js/projects/single.js": "/js/projects/single.js?id=8eef148e30d0fce23eec",
    "/js/offices/single.js": "/js/offices/single.js?id=4d77e62c7ca2ac65987e",
    "/js/admin/index.js": "/js/admin/index.js?id=8176791cb83a5b436e5e",
    "/js/home.js": "/js/home.js?id=f789995879f8addf5849",
    "/js/users/profile.js": "/js/users/profile.js?id=fc244c1867f3b1dfa964",
    "/js/vendor.js": "/js/vendor.js?id=37689510dc7c2ba9709c",
    "/js/errors/404.js": "/js/errors/404.js?id=fbe2711011f694d86bda",
    "/js/auth/login.js": "/js/auth/login.js?id=3fe98833b1f1f9edf2b1",
    "/css/main.css": "/css/main.css?id=b4967c18cc109b8ab4e8",
    "/js/auth/register.js": "/js/auth/register.js?id=a7e026feadb1d1cce718",
    "/js/manifest.js": "/js/manifest.js?id=f1b5ce050f4fbfbffaeb",
    "/css/main.min.css": "/css/main.min.css?id=b4967c18cc109b8ab4e8",
    "/css/editor.css": "/css/editor.css?id=416ddc3977523e1012ae",
    "/css/editor.min.css": "/css/editor.min.css?id=416ddc3977523e1012ae",
    "/js/auth/login.min.js": "/js/auth/login.min.js?id=3fe98833b1f1f9edf2b1",
    "/js/auth/register.min.js": "/js/auth/register.min.js?id=a7e026feadb1d1cce718",
    "/js/errors/404.min.js": "/js/errors/404.min.js?id=fbe2711011f694d86bda",
    "/js/projects/single.min.js": "/js/projects/single.min.js?id=8eef148e30d0fce23eec",
    "/js/teams/single.min.js": "/js/teams/single.min.js?id=28ec2c47e2bc54150972",
    "/js/offices/single.min.js": "/js/offices/single.min.js?id=4d77e62c7ca2ac65987e",
    "/js/users/profile.min.js": "/js/users/profile.min.js?id=fc244c1867f3b1dfa964",
    "/js/admin/index.min.js": "/js/admin/index.min.js?id=8176791cb83a5b436e5e",
    "/js/home.min.js": "/js/home.min.js?id=f789995879f8addf5849",
    "/js/vendor.min.js": "/js/vendor.min.js?id=37689510dc7c2ba9709c"
}